[
  {
    "emisor": "62544518C",
    "receptor": "07447768T",
    "mensaje": "hola",
    "leido": false,
    "contestado": false,
    "borrado": false,
    "fecha": "Nov 26, 2019 6:18:21 PM"
  },
  {
    "emisor": "07447768T",
    "receptor": "62544518C",
    "mensaje": "Buenas",
    "leido": false,
    "contestado": false,
    "borrado": false,
    "fecha": "Nov 26, 2019 6:18:21 PM"
  },
  {
    "emisor": "07447768T",
    "receptor": "62544518C",
    "mensaje": "probando",
    "leido": false,
    "contestado": false,
    "borrado": false,
    "fecha": "Nov 27, 2019 1:31:22 PM"
  },
  {
    "emisor": "07447768T",
    "receptor": "62544518C",
    "mensaje": "probando\nel tamanho\ndel accordion\nal leer mensajes",
    "leido": false,
    "contestado": false,
    "borrado": false,
    "fecha": "Nov 27, 2019 1:54:15 PM"
  },
  {
    "emisor": "62544518C",
    "receptor": "07522677K",
    "mensaje": "Probando envio de mensajes de medico a paciente",
    "leido": false,
    "contestado": false,
    "borrado": false,
    "fecha": "Nov 30, 2019 7:55:22 PM"
  },
  {
    "emisor": "62544518C",
    "receptor": "07522677K",
    "mensaje": "Hola probando",
    "leido": false,
    "contestado": false,
    "borrado": false,
    "fecha": "Nov 30, 2019 10:40:05 PM"
  },
  {
    "emisor": "62544518C",
    "receptor": "07522677K",
    "mensaje": "prueba 1",
    "leido": false,
    "contestado": false,
    "borrado": false,
    "fecha": "Dec 1, 2019 12:02:33 AM"
  },
  {
    "emisor": "62544518C",
    "receptor": "07813720E",
    "mensaje": "hftgjlkoñiugyftdr",
    "leido": false,
    "contestado": false,
    "borrado": false,
    "fecha": "Dec 2, 2019 12:10:28 PM"
  }
]